instructlab/eval/__init__.py
instructlab/eval/_version.py
instructlab/eval/evaluator.py
instructlab/eval/exceptions.py
instructlab/eval/leaderboard.py
instructlab/eval/logger_config.py
instructlab/eval/mmlu.py
instructlab/eval/mt_bench.py
instructlab/eval/mt_bench_answers.py
instructlab/eval/mt_bench_branch_generator.py
instructlab/eval/mt_bench_common.py
instructlab/eval/mt_bench_conversation.py
instructlab/eval/mt_bench_judgment.py
instructlab/eval/mt_bench_model_adapter.py
instructlab/eval/ragas.py
instructlab/eval/data/mt_bench/judge_prompts.jsonl
instructlab/eval/data/mt_bench/question.jsonl
instructlab/eval/data/mt_bench/reference_answer/gpt-4.jsonl
instructlab/eval/data/mt_bench_branch/judge_prompts.jsonl
instructlab_eval-0.6.0.dist-info/licenses/LICENSE
instructlab_eval-0.6.0.dist-info/METADATA
instructlab_eval-0.6.0.dist-info/WHEEL
instructlab_eval-0.6.0.dist-info/entry_points.txt
instructlab_eval-0.6.0.dist-info/top_level.txt
instructlab_eval-0.6.0.dist-info/RECORD
