Metadata-Version: 2.4
Name: instructlab-eval
Version: 0.6.0
Summary: Evaluation
Author-email: InstructLab <dev@instructlab.ai>
License: Apache-2.0
Project-URL: homepage, https://instructlab.ai
Project-URL: source, https://github.com/instructlab/eval
Project-URL: issues, https://github.com/instructlab/eval/issues
Classifier: Development Status :: 3 - Alpha
Classifier: Environment :: Console
Classifier: License :: OSI Approved :: Apache Software License
Classifier: License :: OSI Approved :: MIT License
Classifier: Operating System :: MacOS :: MacOS X
Classifier: Operating System :: POSIX :: Linux
Classifier: Topic :: Scientific/Engineering :: Artificial Intelligence
Classifier: Programming Language :: Python :: 3
Classifier: Programming Language :: Python :: 3.9
Classifier: Programming Language :: Python :: 3.10
Classifier: Programming Language :: Python :: 3.11
Classifier: Programming Language :: Python :: 3.12
Classifier: Programming Language :: Python :: Implementation :: CPython
Requires-Python: >=3.9
License-File: LICENSE
Requires-Dist: GitPython<4.0.0,>=3.1.42
Requires-Dist: shortuuid
Requires-Dist: openai<2.0.0,>=1.13.3
Requires-Dist: psutil
Requires-Dist: torch
Requires-Dist: transformers
Requires-Dist: accelerate
Requires-Dist: pandas
Requires-Dist: pandas-stubs
Requires-Dist: lm-eval>=0.4.4
Requires-Dist: httpx
Requires-Dist: ragas>=0.2.11
Provides-Extra: leaderboard
Requires-Dist: lm-eval[ifeval,math,sentencepiece,vllm]>=0.4.4; extra == "leaderboard"
Requires-Dist: vllm<=0.7.3; extra == "leaderboard"
Requires-Dist: torch<=2.5.1; extra == "leaderboard"
Requires-Dist: strenum>=0.4.15; python_version < "3.11" and extra == "leaderboard"
Requires-Dist: typing-extensions>=4.0.0; python_version < "3.11" and extra == "leaderboard"
Dynamic: license-file
